setup.cfg
setup.py
broffeact/__init__.py
broffeact.egg-info/PKG-INFO
broffeact.egg-info/SOURCES.txt
broffeact.egg-info/dependency_links.txt
broffeact.egg-info/entry_points.txt
broffeact.egg-info/not-zip-safe
broffeact.egg-info/top_level.txt
broffeact/templates/default.html