Metadata-Version: 1.0
Name: broffeact
Version: 0.2.3
Summary: A simple brunch/coffeescript/reactjs documentation generator
Home-page: https://github.com/kursion/broffeact
Author: Yves Lange
Author-email: kursion@gmail.com
License: UNKNOWN
Keywords: coffeescript,documentation,generator,reactjs,brunch
Platform: UNKNOWN
